colvar/__init__.py
colvar/utilities.py
colvar-0.0.1.dist-info/METADATA
colvar-0.0.1.dist-info/WHEEL
colvar-0.0.1.dist-info/top_level.txt
colvar-0.0.1.dist-info/RECORD
