Metadata-Version: 2.1
Name: colvar
Version: 0.0.1
Summary: Package to read COLVAR file
Author: sbhakat (Soumendranath Bhakat)
Author-email: <bhakatsoumendranath@gmail.com>
Keywords: python,COLVAR,Plumed
Classifier: Development Status :: 1 - Planning
Classifier: Intended Audience :: Developers
Classifier: Programming Language :: Python :: 3.8
Classifier: Operating System :: Unix
Classifier: Operating System :: MacOS :: MacOS X
Requires-Dist: numpy
Requires-Dist: pandas
